t2j.py
t2j-0.1.0.dist-info/entry_points.txt
t2j-0.1.0.dist-info/LICENSE
t2j-0.1.0.dist-info/WHEEL
t2j-0.1.0.dist-info/METADATA
t2j-0.1.0.dist-info/RECORD
