Metadata-Version: 2.1
Name: t2j
Version: 0.1.0
Summary: t2j converts TOML input to JSON output and vice versa.
Author-email: "Eugene M. Kim" <astralblue@gmail.com>
Requires-Python: ~=3.3
Classifier: Development Status :: 5 - Production/Stable
Classifier: License :: OSI Approved :: MIT License
Classifier: Programming Language :: Python :: 3
Classifier: Programming Language :: Python :: 3 :: Only
Classifier: Programming Language :: Python :: 3.3
Classifier: Programming Language :: Python :: 3.4
Classifier: Programming Language :: Python :: 3.5
Classifier: Programming Language :: Python :: 3.6
Classifier: Programming Language :: Python :: 3.7
Classifier: Programming Language :: Python :: 3.8
Classifier: Programming Language :: Python :: 3.9
Classifier: Programming Language :: Python :: 3.10
Classifier: Programming Language :: Python :: 3.11
Classifier: Topic :: Utilities
Requires-Dist: tomli>=2
Requires-Dist: tomli_w>=1
Project-URL: Home, https://github.com/astralblue/t2j
